{
  "url": "https://justworkcomplaw.com/qna/injured-at-work-how-to-prove-injury-work-related-in-sandy-utah-96",
  "name": "Proving Work-Related Sandy",
  "@type": "QAPage",
  "@context": "https://schema.org",
  "mainEntity": {
    "name": "How to prove injury work-related in Sandy Utah?",
    "text": "How to prove injury work-related in Sandy Utah?",
    "@type": "Question",
    "answerCount": 2,
    "acceptedAnswer": {
      "text": "Incident report, witness statements, surveillance video, consistent medical records.",
      "@type": "Answer",
      "upvoteCount": 4
    },
    "suggestedAnswer": [
      {
        "text": "Sandy disputes common; gather employer logs, co-worker affidavits. Attorney subpoenas evidence, expert testimony.",
        "@type": "Answer"
      }
    ]
  },
  "description": "Incident report, witness statements, surveillance video, consistent medical records."
}