{
  "url": "https://justworkcomplaw.com/faq/general-multiple-injuries-from-one-accident-at-job-in-sandy-how-does-claim-work-118",
  "name": "Multiple injuries from one accident at job in Sandy, how does claim work?",
  "@type": "FAQPage",
  "@context": "https://schema.org",
  "mainEntity": [
    {
      "name": "Multiple injuries from one accident at job in Sandy, how does claim work?",
      "@type": "Question",
      "acceptedAnswer": {
        "text": "One claim for all; combined disability rating.[4]",
        "@type": "Answer",
        "description": "File one claim covering all body parts; rated together for benefits.[4] Medical for each treated.[2] Key factors: detail all in report; comprehensive eval; combined impairment.[4] List everything initially, full diagnostics, attorney ensures nothing missed.[3] Avoids separate low settlements."
      }
    }
  ],
  "description": "One claim for all; combined disability rating.[4]"
}