{
  "@context": "https://schema.org",
  "@type": "FAQPage",
  "name": "Fell from ladder at work but symptoms started late, can I still claim?",
  "description": "Yes, with medical proof linking to fall; update claim.[3]",
  "url": "https://justworkcomplaw.com/faq/general-fell-from-ladder-at-work-but-symptoms-started-late-can-i-still-claim-137",
  "mainEntity": [
    {
      "@type": "Question",
      "name": "Fell from ladder at work but symptoms started late, can I still claim?",
      "acceptedAnswer": {
        "@type": "Answer",
        "text": "Yes, with medical proof linking to fall; update claim.[3]",
        "description": "Yes, delayed symptoms from ladder falls like back pain qualify if linked to the incident by medical evidence.[3]\n\nReport promptly and update your claim with new doctor findings.[1] Insurers challenge causation.\n\n- See specialist for causation letter.\n- Keep dated symptom journal.\n- File amendments.\n\nLawyer connects dots for approval; don't delay reporting.[2]"
      }
    }
  ]
}