{
  "url": "https://justworkcomplaw.com/faq/general-no-witnesses-to-my-ladder-fall-at-work-do-i-have-a-case-139",
  "name": "No witnesses to my ladder fall at work, do I have a case?",
  "@type": "FAQPage",
  "@context": "https://schema.org",
  "mainEntity": [
    {
      "name": "No witnesses to my ladder fall at work, do I have a case?",
      "@type": "Question",
      "acceptedAnswer": {
        "text": "Yes, use photos, medical, report; no witnesses not fatal.[3]",
        "@type": "Answer",
        "description": "Yes, your medical records, photos, and incident report suffice; circumstantial evidence like ladder condition supports.[3][5]\n\nSupervisor acknowledgment or OSHA logs help; many claims succeed without eyes.[1]\n\n- Self-document immediately.\n- Preserve ladder.\n- Corroborate with gear.\n\nLawyer builds case from available proof; don't assume no case.[2]"
      }
    }
  ],
  "description": "Yes, use photos, medical, report; no witnesses not fatal.[3]"
}