{
  "url": "https://justworkcomplaw.com/faq/occupational-illness-what-s-the-difference-between-work-injury-and-occupational-illness-claim-in-murr-242",
  "name": "What's the difference between work injury and occupational illness claim in Murray?",
  "@type": "FAQPage",
  "@context": "https://schema.org",
  "mainEntity": [
    {
      "name": "What's the difference between work injury and occupational illness claim in Murray?",
      "@type": "Question",
      "acceptedAnswer": {
        "text": "Illnesses gradual/exposure vs. sudden injuries; both compensable with proof.[1]",
        "@type": "Answer",
        "description": "Injuries are sudden events; illnesses gradual like repetitive or exposure diseases, both covered under AOE/COE in Utah.[1] Illnesses need stronger causation.[1] Key factors: No single incident for illness; latency ok; same benefits.[1] File same way but emphasize medical nexus for illnesses. Know distinction avoids denials."
      }
    }
  ],
  "description": "Illnesses gradual/exposure vs. sudden injuries; both compensable with proof.[1]"
}